spotify_client.py
test.py
tune.py
tunecli-0.1.0.dist-info/licenses/LICENSE
tunecli-0.1.0.dist-info/METADATA
tunecli-0.1.0.dist-info/WHEEL
tunecli-0.1.0.dist-info/entry_points.txt
tunecli-0.1.0.dist-info/top_level.txt
tunecli-0.1.0.dist-info/RECORD
