Metadata-Version: 2.4
Name: tunecli
Version: 0.1.0
Summary: CLI to play Spotify songs from terminal
Author-email: Shrish Pellakur <shrishtg@example.com>
License: MIT
Requires-Python: >=3.10
License-File: LICENSE
Requires-Dist: spotipy>=2.25.1
Requires-Dist: click>=8.0
Dynamic: license-file
